eon/__init__.py
eon/_eon.abi3.so
eon/lib.rs
eon_py-0.1.8.dist-info/METADATA
eon_py-0.1.8.dist-info/WHEEL
eon_py-0.1.8.dist-info/RECORD
